ipydrawio_export/__init__.py
ipydrawio_export/_version.py
ipydrawio_export/app.py
ipydrawio_export/constants.py
ipydrawio_export/handlers.py
ipydrawio_export/manager.py
ipydrawio_export/serverextension.py
ipydrawio_export/etc/install.json
ipydrawio_export/etc/jupyter_notebook_config.d/ipydrawio-export.json
ipydrawio_export/etc/jupyter_server_config.d/ipydrawio-export.json
ipydrawio_export/vendor/draw-image-export2/LICENSE
ipydrawio_export/vendor/draw-image-export2/README.md
ipydrawio_export/vendor/draw-image-export2/app.json
ipydrawio_export/vendor/draw-image-export2/export.js
ipydrawio_export/vendor/draw-image-export2/package.json
ipydrawio_export/vendor/draw-image-export2/yarn.lock
ipydrawio_export-1.3.0.data/data/etc/jupyter/jupyter_notebook_config.d/ipydrawio-export.json
ipydrawio_export-1.3.0.data/data/etc/jupyter/jupyter_server_config.d/ipydrawio-export.json
ipydrawio_export-1.3.0.data/data/share/jupyter/labextensions/@deathbeds/ipydrawio-pdf/install.json
ipydrawio_export-1.3.0.data/data/share/jupyter/labextensions/@deathbeds/ipydrawio-pdf/package.json
ipydrawio_export-1.3.0.data/data/share/jupyter/labextensions/@deathbeds/ipydrawio-pdf/static/385.1639e823caa9b50aada5.js
ipydrawio_export-1.3.0.data/data/share/jupyter/labextensions/@deathbeds/ipydrawio-pdf/static/568.c1c4c11fee97c25006f5.js
ipydrawio_export-1.3.0.data/data/share/jupyter/labextensions/@deathbeds/ipydrawio-pdf/static/remoteEntry.a38839e484daf1046bb6.js
ipydrawio_export-1.3.0.data/data/share/jupyter/labextensions/@deathbeds/ipydrawio-pdf/static/style.js
ipydrawio_export-1.3.0.data/data/share/jupyter/labextensions/@deathbeds/ipydrawio-pdf/static/third-party-licenses.json
ipydrawio_export-1.3.0.dist-info/LICENSE.txt
ipydrawio_export-1.3.0.dist-info/METADATA
ipydrawio_export-1.3.0.dist-info/WHEEL
ipydrawio_export-1.3.0.dist-info/entry_points.txt
ipydrawio_export-1.3.0.dist-info/top_level.txt
ipydrawio_export-1.3.0.dist-info/RECORD
